geo_vtk/data/2d_data/ahn3_05m_dtm_merge.vtk
geo_vtk/data/2d_data/ahn3_05m_dtm_merge_2d.vtk
geo_vtk/data/2d_data/ahn3_05m_dtm_merge_3d.vtk
geo_vtk/data/2d_data/ahn3_05m_dtm_merge_interp_3d.vtk
geo_vtk/data/2d_data/em_data.csv
geo_vtk/data/2d_data/ert_coordiantes.txt
geo_vtk/data/2d_data/ert_resutls.xyz
geo_vtk/data/Boreholes/ERT_boreholesxyz.xlsx
geo_vtk/data/Boreholes/F1.txt
geo_vtk/data/Boreholes/F2.txt
geo_vtk/data/Boreholes/F3.txt
geo_vtk/data/Boreholes/F4.txt
geo_vtk/data/Boreholes/F5.txt
geo_vtk/data/Boreholes/F6.txt
geo_vtk/data/Boreholes/F7.txt
geo_vtk/data/Boreholes/F8.txt
geo_vtk/data/Boreholes/MH1.txt
geo_vtk/data/Boreholes/MH2.txt
geo_vtk/data/Boreholes/MH3.txt
geo_vtk/data/arcgis/S7_boorbeschrijvingen.pdf
geo_vtk/data/arcgis/d50_1m.ASC.xml
geo_vtk/data/arcgis/d50_1m.asc
geo_vtk/data/arcgis/d50_1m.asc.aux.xml
geo_vtk/data/arcgis/d50_1m.prj
geo_vtk/data/arcgis/d50_1m.vtk
geo_vtk/data/arcgis/gebied_S7-20.cpg
geo_vtk/data/arcgis/gebied_S7-20.dbf
geo_vtk/data/arcgis/gebied_S7-20.prj
geo_vtk/data/arcgis/gebied_S7-20.sbn
geo_vtk/data/arcgis/gebied_S7-20.sbx
geo_vtk/data/arcgis/gebied_S7-20.shp
geo_vtk/data/arcgis/gebied_S7-20.shp.xml
geo_vtk/data/arcgis/gebied_S7-20.shx
geo_vtk/data/arcgis/noordzee_vak_S7.xml
geo_vtk/data/arcgis/seismieklistS7.txt
geo_vtk/data/arcgis/uitgevoerde_boringen_NITGnr_S7-20.cpg
geo_vtk/data/arcgis/uitgevoerde_boringen_NITGnr_S7-20.dbf
geo_vtk/data/arcgis/uitgevoerde_boringen_NITGnr_S7-20.prj
geo_vtk/data/arcgis/uitgevoerde_boringen_NITGnr_S7-20.sbn
geo_vtk/data/arcgis/uitgevoerde_boringen_NITGnr_S7-20.sbx
geo_vtk/data/arcgis/uitgevoerde_boringen_NITGnr_S7-20.shp
geo_vtk/data/arcgis/uitgevoerde_boringen_NITGnr_S7-20.shx
geo_vtk/data/images/3d.jpg
geo_vtk/data/images/geotop_dense.png
geo_vtk/data/images/logo-deltares-groot.png
geo_vtk/data/images/overview.png
geo_vtk/data/images/overview_ert_no_3.png
geo_vtk/data/vtk/F1.vtk
geo_vtk/data/vtk/F2.vtk
geo_vtk/data/vtk/F3.vtk
geo_vtk/data/vtk/F4.vtk
geo_vtk/data/vtk/F5.vtk
geology-1.0.0.dist-info/licenses/LICENSE
geology-1.0.0.dist-info/METADATA
geology-1.0.0.dist-info/WHEEL
geology-1.0.0.dist-info/entry_points.txt
geology-1.0.0.dist-info/top_level.txt
geology-1.0.0.dist-info/RECORD
