Metadata-Version: 2.4
Name: Geology
Version: 1.0.0
Summary: Professional geological model reconstruction using advanced inpainting techniques
Home-page: https://github.com/mariosgeo/Geology
Author: Marios Karaoulis
Author-email: Marios Karaoulis <marios.karaoulis@example.com>
Maintainer: Marios Karaoulis
Maintainer-email: Marios Karaoulis <marios.karaoulis@example.com>
License: MIT
Project-URL: Homepage, https://github.com/mariosgeo/Geology
Project-URL: Documentation, https://github.com/mariosgeo/Geology/wiki
Project-URL: Repository, https://github.com/mariosgeo/Geology
Project-URL: Bug Tracker, https://github.com/mariosgeo/Geology/issues
Project-URL: Changelog, https://github.com/mariosgeo/Geology/blob/main/CHANGELOG.md
Project-URL: Research Paper, https://doi.org/10.1000/example
Keywords: geology,geophysics,inpainting,machine-learning,geological-modeling,biharmonic-interpolation,subsurface,borehole-data,geological-reconstruction,earth-science,spatial-analysis,geological-uncertainty,one-vs-all
Platform: any
Classifier: Development Status :: 4 - Beta
Classifier: Intended Audience :: Science/Research
Classifier: Intended Audience :: Education
Classifier: Intended Audience :: Developers
Classifier: Topic :: Scientific/Engineering :: GIS
Classifier: Topic :: Scientific/Engineering :: Artificial Intelligence
Classifier: Topic :: Scientific/Engineering :: Image Processing
Classifier: Topic :: Scientific/Engineering :: Mathematics
Classifier: Topic :: Scientific/Engineering :: Physics
Classifier: License :: OSI Approved :: MIT License
Classifier: Programming Language :: Python :: 3
Classifier: Programming Language :: Python :: 3.8
Classifier: Programming Language :: Python :: 3.9
Classifier: Programming Language :: Python :: 3.10
Classifier: Programming Language :: Python :: 3.11
Classifier: Operating System :: OS Independent
Classifier: Operating System :: Microsoft :: Windows
Classifier: Operating System :: POSIX :: Linux
Classifier: Operating System :: MacOS
Requires-Python: >=3.8
License-File: LICENSE
Requires-Dist: numpy>=1.21.0
Requires-Dist: matplotlib>=3.5.0
Requires-Dist: scipy>=1.8.0
Requires-Dist: pandas>=1.4.0
Requires-Dist: scikit-image>=0.19.0
Requires-Dist: scikit-learn>=1.1.0
Requires-Dist: geopandas>=0.11.0
Requires-Dist: shapely>=1.8.0
Requires-Dist: vtk>=9.0.0
Requires-Dist: alphashape>=1.3.0
Requires-Dist: descartes>=1.1.0
Requires-Dist: jupyter>=1.0.0
Requires-Dist: ipykernel>=6.0.0
Requires-Dist: openpyxl>=3.0.0
Provides-Extra: dev
Requires-Dist: pytest>=7.0.0; extra == "dev"
Requires-Dist: pytest-cov>=3.0.0; extra == "dev"
Requires-Dist: black>=22.0.0; extra == "dev"
Requires-Dist: flake8>=4.0.0; extra == "dev"
Requires-Dist: isort>=5.10.0; extra == "dev"
Requires-Dist: sphinx>=4.0.0; extra == "dev"
Requires-Dist: sphinx-rtd-theme>=1.0.0; extra == "dev"
Requires-Dist: nbsphinx>=0.8.0; extra == "dev"
Requires-Dist: pre-commit>=2.15.0; extra == "dev"
Requires-Dist: ipdb>=0.13.0; extra == "dev"
Requires-Dist: memory-profiler>=0.60.0; extra == "dev"
Provides-Extra: visualization
Requires-Dist: pyvista>=0.36.0; extra == "visualization"
Requires-Dist: mayavi>=4.7.0; extra == "visualization"
Requires-Dist: plotly>=5.0.0; extra == "visualization"
Requires-Dist: seaborn>=0.11.0; extra == "visualization"
Requires-Dist: holoviews>=1.14.0; extra == "visualization"
Requires-Dist: bokeh>=2.4.0; extra == "visualization"
Requires-Dist: ipywidgets>=7.6.0; extra == "visualization"
Provides-Extra: geospatial
Requires-Dist: rasterio>=1.3.0; extra == "geospatial"
Requires-Dist: xarray>=0.20.0; extra == "geospatial"
Requires-Dist: contextily>=1.2.0; extra == "geospatial"
Requires-Dist: folium>=0.12.0; extra == "geospatial"
Requires-Dist: cartopy>=0.20.0; extra == "geospatial"
Requires-Dist: pyproj>=3.3.0; extra == "geospatial"
Requires-Dist: fiona>=1.8.0; extra == "geospatial"
Provides-Extra: ml
Requires-Dist: tensorflow>=2.8.0; extra == "ml"
Requires-Dist: torch>=1.11.0; extra == "ml"
Requires-Dist: xgboost>=1.6.0; extra == "ml"
Requires-Dist: lightgbm>=3.3.0; extra == "ml"
Provides-Extra: all
Requires-Dist: geology-inpainting[dev,geospatial,ml,visualization]; extra == "all"
Dynamic: author
Dynamic: home-page
Dynamic: license-file
Dynamic: maintainer
Dynamic: platform
Dynamic: requires-python
